pubmed_mcp/__init__.py
pubmed_mcp/pyproject.toml
pubmed_mcp/server.py
yxtpm_chaxun-0.1.0.dist-info/METADATA
yxtpm_chaxun-0.1.0.dist-info/WHEEL
yxtpm_chaxun-0.1.0.dist-info/entry_points.txt
yxtpm_chaxun-0.1.0.dist-info/RECORD
