Metadata-Version: 2.4
Name: yxtpm-chaxun
Version: 0.1.0
Summary: Add your description here
Author-email: zargabaath <15122150377@163.com>
Requires-Python: >=3.11
Requires-Dist: httpx>=0.28.1
Requires-Dist: mcp[cli]>=1.13.1
